{
	"pcode": "E0000015",
	"LawLevel": "法律",
	"name": "外交部領事事務局組織法",
	"category": [
		"行政",
		"外交部",
		"組織目"
	],
	"LawModifiedDate": "20111114",
	"EngLawName": "Organization Act of the Bureau of Consular Affairs, Ministry of Foreign Affairs",
	"histories": [
		"一百年十一月十四日總統華總一義字第 10000252451 號令制定公布全文 6 條；施行日期，由行政院以命令定之；一百零一年二月十六日行政院院授研綜字第 1012260097 號令發布定自一百零一年九月一日施行"
	],
	"articles": [
		{
			"number": 100,
			"content": [
				{
					"text": "外交部為辦理領事事務，特設領事事務局（以下簡稱本局）。"
				}
			]
		},
		{
			"number": 200,
			"content": [
				{
					"text": "本局掌理下列事項：",
					"children": [
						{
							"text": "一、中華民國護照與加簽之核發及執行。"
						},
						{
							"text": "二、外國護照簽證之核發。"
						},
						{
							"text": "三、領事事務文件證明之執行。"
						},
						{
							"text": "四、旅外國人急難救助之協調及聯繫。"
						},
						{
							"text": "五、與地方政府、民間團體辦理城市外交、國際活動之聯繫及執行。"
						},
						{
							"text": "六、領事事務資訊系統之規劃、執行及運用。"
						},
						{
							"text": "七、其他有關領事事務事項。"
						}
					]
				}
			]
		},
		{
			"number": 300,
			"content": [
				{
					"text": "本局置局長一人，職務列簡任第十三職等；副局長二人，職務列簡任第十二職等。"
				}
			]
		},
		{
			"number": 400,
			"content": [
				{
					"text": "本局置主任秘書，職務列簡任第十一職等。"
				}
			]
		},
		{
			"number": 500,
			"content": [
				{
					"text": "本局各職稱之官等職等及員額，另以編制表定之。"
				}
			]
		},
		{
			"number": 600,
			"content": [
				{
					"text": "本法施行日期，由行政院以命令定之。"
				}
			]
		}
	]
}