{
  "LawLevel": "命令",
  "LawName": "交通部觀光局大鵬灣國家風景區管理處籌備處暫行組織規程",
  "LawURL": "https://law.moj.gov.tw/LawClass/LawAll.aspx?pcode=K0000043",
  "LawCategory": "廢止法規＞交通部",
  "LawModifiedDate": "19971116",
  "LawEffectiveDate": "",
  "LawEffectiveNote": "",
  "LawAbandonNote": "廢",
  "LawHasEngVersion": "N",
  "EngLawName": "",
  "LawAttachements": [],
  "LawHistories": "1.中華民國八十五年四月十六日交通部（85）交人發字第 8514 號令訂定\r\n  發布全文 11 條\r\n2.中華民國八十六年十一月十六日交通部（86）交人發字第 8683 號令發\r\n  布廢止本組織規程",
  "LawForeword": "",
  "LawArticles": [
    {
      "ArticleType": "A",
      "ArticleNo": "第 1 條",
      "ArticleContent": "交通部觀光局為辦理大鵬灣風景特定區 (以下簡稱本區) 觀光遊憩資源之\r\n調查、規劃及開發與籌備大鵬灣國家風景區管理處有關事宜，特設立交通\r\n部觀光局大鵬灣國家風景區管理處籌備處 (以下簡稱本處) 。"
    },
    {
      "ArticleType": "A",
      "ArticleNo": "第 2 條",
      "ArticleContent": "本處掌理左列事項：\r\n一、研擬風景特定區計畫相關作業及未來開發計畫項目之管制制度事項。\r\n二、鼓勵民間參與本區之開發建設事項。\r\n三、本區土地利用與取得之協調、執行事項。\r\n四、本區整體發展規劃計委辦案及其相關研究計畫之監督、執行事項。\r\n五、本區開發建設之執行及環境品質之改善、監測及維護事項。\r\n六、本區現有遊憩設施之整建及維護事項。\r\n七、本區開發計畫之環境影響評估規劃作業事項。\r\n八、本區軍事設施之搬遷事項。\r\n九、本區及其附近區域觀光資源之調查、規劃、開發及保育事項。\r\n十、擬定及執行各項經營管理、安全督導計畫及規範事項。\r\n十一、各項觀光活動之推廣及宣傳事項。\r\n十二、籌辦交通部觀光局大鵬灣國家風景區管理處之成立有關事項。"
    },
    {
      "ArticleType": "A",
      "ArticleNo": "第 3 條",
      "ArticleContent": "本處設企劃課、工務課及管理課，分別掌理前條所列事項。"
    },
    {
      "ArticleType": "A",
      "ArticleNo": "第 4 條",
      "ArticleContent": "本處設秘書室，掌理文書、研考、印信、出納、庶務、財務管理及其他不\r\n屬於各課之事項。"
    },
    {
      "ArticleType": "A",
      "ArticleNo": "第 5 條",
      "ArticleContent": "本處置處長一人，綜理處務，並指揮、監督所屬員工。"
    },
    {
      "ArticleType": "A",
      "ArticleNo": "第 6 條",
      "ArticleContent": "本處置秘書、技正、課長、課員、技士、技佐、辦事員。"
    },
    {
      "ArticleType": "A",
      "ArticleNo": "第 7 條",
      "ArticleContent": "本處置人事管理員，由交通部觀光局指派適當人員兼任，依法辦理人事管\r\n理事項。"
    },
    {
      "ArticleType": "A",
      "ArticleNo": "第 8 條",
      "ArticleContent": "本處置會計員，由交通部觀光局指派適當人員兼任，依法辦理歲計、會計\r\n事項，並兼辦統計事項。"
    },
    {
      "ArticleType": "A",
      "ArticleNo": "第 9 條",
      "ArticleContent": "本規程所列各職稱之官等及員額，另以編制表定之。\r\n各職稱之職等，依職務列等表之規定。"
    },
    {
      "ArticleType": "A",
      "ArticleNo": "第 10 條",
      "ArticleContent": "本處於交通部觀光局大鵬灣國家風景區管理處成立時裁撤之；其現任人員\r\n除具有合法資格轉任者外，應予資遺。"
    },
    {
      "ArticleType": "A",
      "ArticleNo": "第 11 條",
      "ArticleContent": "本規程自中華民國八十五年三月二十一日施行。"
    }
  ]
}