{
	"pcode": "O0050008",
	"LawLevel": "命令",
	"name": "環境衛生用藥廢容器回收清除處理辦法",
	"category": [
		"廢止法規",
		"行政院環境保護署"
	],
	"LawModifiedDate": "19970910",
	"discarded": true,
	"histories": [
		"七十九年八月二十日經濟部（79）經工字第 36901 號令、行政院環境保護署（79）環署廢字第 29195 號令訂定發布全文 21 條",
		"八十三年七月二十九日經濟部（83）經工字第 08702 號令、 行政院環境保護署（83）環署廢字第 34439 號令會銜修正發布全文 2 9 條",
		"八十六年九月十日行政院環境保護署（86）環署廢字第 48769 號令、經濟部（86）經工字第 86215198 號令會銜發布廢止"
	],
	"articles": [
		{
			"number": 100,
			"content": [
				{
					"text": "本辦法依廢棄物清理法第十條之一第二項規定訂定之。"
				}
			]
		},
		{
			"number": 200,
			"content": [
				{
					"text": "本辦法專用名詞定義如左：",
					"children": [
						{
							"text": "一、環境衛生用藥：指一般環境衛生用藥、特殊環境衛生用藥及其原體，包括殺蟲劑、殺蟎劑、殺鼠劑、殺菌劑及其他經中央主管機關核定之用藥。"
						},
						{
							"text": "二、一般環境衛生用藥：指以環境衛生用藥原體經加工調製，不用其原名稱，所含之主成分不超過中央主管機關所規定之限量，耐久儲存，使用簡便之藥品。"
						},
						{
							"text": "三、特殊環境衛生用藥：指以環境衛生用藥原體經加工調製而需稀釋或在安全防護措施下，限由各級主管機關及所屬機關或病媒防治業者使用之環境衛生用藥。"
						},
						{
							"text": "四、環境衛生用藥原體：指用以製造一般及特殊環境衛生用藥所需之有效成分。"
						},
						{
							"text": "五、環境衛生用藥廢容器：指以塑膠、玻璃、金屬、紙、鋁箔或其他經中央主管機關公告之單一或複合材質製成，用以直接裝填環境衛生用藥並經廢棄之容器。"
						},
						{
							"text": "六、環境衛生用藥製造業者：指經營環境衛生用藥之製造、加工、分裝及自製產品批發、零售、輸出、輸入原體之業者。"
						},
						{
							"text": "七、環境衛生用藥販賣業者：指經營環境衛生用藥之批發、零售、輸入及輸出業者。但不包括一般環境衛生用藥之批發商及零售商。"
						},
						{
							"text": "八、一般環境衛生用藥批發商、零售商：指販賣一般環境衛生用藥之批發商、零售商。"
						},
						{
							"text": "九、押金：指為回收環境衛生用藥廢容器，預先收取並於回收後退回之費用。"
						},
						{
							"text": "十、回收率：指一定期間內環境衛生用藥業者回收之環境衛生用藥廢容器量與在國內所銷售之環境衛生用藥容器量之百分比。"
						},
						{
							"text": "十一、回收清除費用或收入：指回收清除環境衛生用藥廢容器所支出之費用或獲得之收入。"
						},
						{
							"text": "十二、處理費用或收入：指處理環境衛生用藥廢容器所支出之費用或獲得之收入。"
						},
						{
							"text": "十三、地區性回收站、回收中心：回收之環境衛生用藥廢容器地區性貯存場所。"
						}
					]
				}
			]
		},
		{
			"number": 300,
			"content": [
				{
					"text": "中央主管機關得視實際情況，指定環境衛生用藥製造、販賣業者 (以下簡稱環境衛生用藥業者) 於指定公告日起三個月內檢具申請書向省 (市) 主管機關申請登記。前項申請書格式由中央主管機關定之。申請登記之辦理，省主管機關得授權縣 (市) 主管機關為之。"
				}
			]
		},
		{
			"number": 400,
			"content": [
				{
					"text": "環境衛生用藥業者應依環境衛生用藥之規格，回收環境衛生用藥廢容器。"
				}
			]
		},
		{
			"number": 500,
			"content": [
				{
					"text": "環境衛生用藥業者得依左列方式執行環境衛生用藥廢容器之回收工作：",
					"children": [
						{
							"text": "一、委託公、民營廢棄物清除、處理機構。"
						},
						{
							"text": "二、委託財團法人一般廢棄物回收清除處理基金會。"
						},
						{
							"text": "三、設置地區性回收站、回收中心。"
						},
						{
							"text": "四、銷售系統逆流回收。"
						},
						{
							"text": "五、押金方式。"
						},
						{
							"text": "六、其他經中央主管機關核可之方式。"
						}
					]
				}
			]
		},
		{
			"number": 600,
			"content": [
				{
					"text": "環境衛生用藥業者除中央主管機關另定提報日期者外，應於本辦法發布日起三個月內，檢具回收清除計畫書送省 (市) 主管機關審核後，轉請中央主管機關核備。委託回收清除者，應檢附契約書。"
				}
			]
		},
		{
			"number": 700,
			"content": [
				{
					"text": "前條回收清除計畫書，應載明左列事項：",
					"children": [
						{
							"text": "一、預估環境衛生用藥之年營業量。"
						},
						{
							"text": "二、預估回收量。"
						},
						{
							"text": "三、地區性回收站、回收中心之名稱、地點及其承諾書等詳細資料。"
						},
						{
							"text": "四、回收方式、架構及回收系統運作之方法。"
						},
						{
							"text": "五、回收率監測紀錄措施。"
						},
						{
							"text": "六、回收宣導計書。"
						},
						{
							"text": "七、緊急應變措施。"
						},
						{
							"text": "八、其他經中央主管機關指定之事項。"
						}
					]
				},
				{
					"text": "環境衛生用藥業者採押金方式回收者，並應載明押金數額及其管理方法。"
				}
			]
		},
		{
			"number": 800,
			"content": [
				{
					"text": "環境衛生用藥業者每一定期間應達成之回收率，由中央主管機關會商中央目的事業主管機關依環境衛生用藥容器材質及裝填內容物種類公告之。"
				},
				{
					"text": "前項有關特殊環境衛生用藥回收率之計算，其尚未使用量應檢具證明文件始得扣除，並應於使用後併入該期間之營業量計算。"
				}
			]
		},
		{
			"number": 900,
			"content": [
				{
					"text": "環境衛生用藥業者執行回收環境衛生用藥廢容器，連續二年未達公告回收率，中央主管機關得依環境衛生用藥容器材質及裝填內容物種類，指定公告環境衛生用藥業者採押金方式回收。"
				}
			]
		},
		{
			"number": 1000,
			"content": [
				{
					"text": "環境衛生用藥業者應於環境衛生用藥容器明顯處標示回收標誌及材質；採押金方式回收者，並應標明押金數額及退費方式，報請中央主管機關核備。"
				},
				{
					"text": "前項押金數額如有變更，應於變更前三個月提報中央主管機關核備。"
				}
			]
		},
		{
			"number": 1100,
			"content": [
				{
					"text": "環境衛生用藥業者採押金方式執行回收並將押金退回之方式如左：",
					"children": [
						{
							"text": "一、設置回收點。"
						},
						{
							"text": "二、委託公、民營廢棄物清除、處理機構。"
						},
						{
							"text": "三、委託財團法人一般廢棄物回收清除處理基金會。"
						},
						{
							"text": "四、其他經中央主管機關公告之回收方式。"
						}
					]
				},
				{
					"text": "前項第一款之數量、地點應併入回收清除計畫書提報省 (市) 主管機關審核後轉請中央主管機關核備；其涉及販賣店、零售店回收者，應訂定承諾書或契約書。"
				}
			]
		},
		{
			"number": 1200,
			"content": [
				{
					"text": "一般環境衛生用藥批發商、零售商應依左列規定推動一般環境衛生用藥廢容器回收工作：",
					"children": [
						{
							"text": "一、宣導一般環境衛生用藥廢容器應回收之規定事項。"
						},
						{
							"text": "二、依回收清除計畫之內容配合執行回收工作。"
						},
						{
							"text": "三、其他經中央主管機關公告之事項。"
						}
					]
				}
			]
		},
		{
			"number": 1300,
			"content": [
				{
					"text": "環境衛生用藥業者回收之環境衛生用藥廢容器，應自行、委託公、民營廢棄物處理機構或依其他經中央主管機關認可之方式負責處理，除經中央主管機關另定提報日期者外，應於本辦法發布日起六個月內，檢具環境衛生用藥廢容器處理計畫書，送省 (市) 主管機關審核後，轉請中央主管機關核備。委託處理者，應檢附契約書。"
				}
			]
		},
		{
			"number": 1400,
			"content": [
				{
					"text": "前條處理計書書應載明左列事項：",
					"children": [
						{
							"text": "一、預估處理量。"
						},
						{
							"text": "二、環境衛生用藥廢容器進廠(場)數量監測及管理方法。"
						},
						{
							"text": "三、環境衛生用藥廢容器貯存方法及設施。"
						},
						{
							"text": "四、處理之方式、期程及污染防治措施。"
						},
						{
							"text": "五、處理設施設置進度。"
						},
						{
							"text": "六、事業廢棄物清理方法及設施。"
						},
						{
							"text": "七、緊急應變措施。"
						},
						{
							"text": "八、其他經中央主管機關指定之事項。"
						}
					]
				}
			]
		},
		{
			"number": 1500,
			"content": [
				{
					"text": "環境衛生用藥業者依本辦法第六條、第十三條所提之回收清除計畫書、處理計畫書內容涉及左列事頃之變更者，應於變更前一個月內提報變更計畫，送省 (市) 主管機關審核後轉請中央主管機關核備：",
					"children": [
						{
							"text": "一、執行回收方式。"
						},
						{
							"text": "二、地區性回收站、回收中心之回收運作系統。"
						},
						{
							"text": "三、環境衛生用藥廢容器之處理方式。"
						},
						{
							"text": "四、其他經中央主管機關指定者。"
						}
					]
				}
			]
		},
		{
			"number": 1600,
			"content": [
				{
					"text": "環境衛生用藥業者應於每月結束後一個月內，向貯存場所及處理廠 (場)所在地之當地主管機關申報上月份回收量及處理量；縣 (市) 主管機關應於審核後報請省主管機關備查。"
				},
				{
					"text": "前項申報期限，中央主管機關為查核需要，得規定於一定期間採每週申報方式為之。"
				},
				{
					"text": "第一項處理量有輸出國外或大陸地區者，應於輸出前報經貯存場所及處理廠 (場) 之當地主管機關備查。"
				}
			]
		},
		{
			"number": 1700,
			"content": [
				{
					"text": "環境衛生用藥業者應依所提回收清除計畫書、處理計畫書記載事項，妥善回收清除處理環境衛生用藥廢容器，並依左列規定檢具相關證明文件向省(市) 主管機關申報，經審核後轉請中央主管機關備查：",
					"children": [
						{
							"text": "一、每季結束後四十五日內申報環境衛生用藥容器營業量、輸出量、環境衛生用藥廢容器回收量及處理量。"
						},
						{
							"text": "二、公告回收率期間屆滿日起四十五日內，申報回收率。"
						},
						{
							"text": "三、其他經中央主管機關指定之事項。"
						}
					]
				},
				{
					"text": "前項申報之辦理，省主管機關得授權縣 (市) 主管機關為之。"
				}
			]
		},
		{
			"number": 1800,
			"content": [
				{
					"text": "環境衛生用藥業者回收、處理環境衛生用藥廢容器總量之計算，應以報經省 (市) 主管機關核備之貯存場所、處理廠 (場) 之回收量、處理量為準。前項回收之環境衛生用藥廢容器貯存以二年限，延長時須先報經當地主管機關核准。"
				}
			]
		},
		{
			"number": 1900,
			"content": [
				{
					"text": "環境衛生用藥廢容器之貯存、清除處理方法及其設施，準用事業廢棄物貯存清除處理方法及設施標準有關之規定。"
				}
			]
		},
		{
			"number": 2000,
			"content": [
				{
					"text": "環境衛生用藥業者為執行環境衛生用藥廢容器回收清除處理工作，得聯合成立共同回收清除處理組織 (以下簡稱共同組織) ；共同組織向參加業者收取費用之標準，應報請中央主管機關核定。"
				}
			]
		},
		{
			"number": 2100,
			"content": [
				{
					"text": "環境衛生用藥業者成立共同組織執行回收清除、處理工作，左列事項得由共同組織辦理：",
					"children": [
						{
							"text": "一、依第三條規定申請登記。"
						},
						{
							"text": "二、依第六條規定提報回收清除計畫書。"
						},
						{
							"text": "三、依第十三條規定提報處理計畫書。"
						},
						{
							"text": "四、依第十五條規定提報變更計畫書。"
						},
						{
							"text": "五、依第十六條規定申報貯存場所及處理廠 (場) 之回收量及處理量。"
						},
						{
							"text": "六、依第十七條規定申報環境衛生用藥容器營業量、輸出量、環境衛生用藥廢容器回收量、處理量及回收率。"
						},
						{
							"text": "七、其他經中央主管機關認可之事項。"
						}
					]
				}
			]
		},
		{
			"number": 2200,
			"content": [
				{
					"text": "中央主管機關得成立財團法人一般廢棄物回收清除處理基金會 (以下簡稱基金會) ，協助推動環境衛生用藥廢容器回收清除處理工作。"
				}
			]
		},
		{
			"number": 2300,
			"content": [
				{
					"text": "基金會得視實際情形，給付費用委託執行機關或公、民營廢棄物清除、處理機構執行環境衛生用藥廢容器回收清除處理工作。"
				}
			]
		},
		{
			"number": 2400,
			"content": [
				{
					"text": "共同組織執行環境衛生用藥廢容器之回收清除處理工作，向參加業者收取之費用或獲得之收入，應成立專戶保管運用，並依本辦法第二條第十一款及第十二款之規定內容分帳列管。"
				},
				{
					"text": "前項回收清除處理工作，如採押金方式者，應增設押金專戶。"
				},
				{
					"text": "環境衛生用藥業者採押金方式執行回收，得於回收率申報後次月將未回收環境衛生用藥廢容器之押金繳交基金會。如回收量超過營業量時，得向基金會申請退回已繳交該部分之押金。"
				}
			]
		},
		{
			"number": 2500,
			"content": [
				{
					"text": "共同組織及基金會之經費收支及運用管理，應訂定實施要點，報請中央主管機關核定，並依實施要點每年定期提報必要資料送中央主管機關核備。"
				},
				{
					"text": "前項有關會計報告書資料應經依法登記執業之會計師簽證。"
				}
			]
		},
		{
			"number": 2600,
			"content": [
				{
					"text": "主管機關得派員檢查環境衛生用藥業者之產銷、營運、共同組織或基金會回收清除處理及經費運用管理情形，或至貯存場所、處理廠 (場) 查核索取有關資料，必要時，並得聘請會計師或會同有關機關查核。"
				},
				{
					"text": "前項查核，環境衛生用藥業者、共同組織、公、民營廢棄物清除、處理機構、地區性回收站及回收中心或基金會不得拒絕。"
				}
			]
		},
		{
			"number": 2700,
			"content": [
				{
					"text": "環境衛生用藥業者、共同組織、基金會及接受環境衛生用藥業者委託之公、民營廢物清除、處理機構，應將有關回收清除、處理之計量單據及其他足以證明回收清除、處理量之憑證保存五年。"
				}
			]
		},
		{
			"number": 2800,
			"content": [
				{
					"text": "環境衛生用藥業者於指定後設立者，應自設立後三個月內依第三條規定申請登記。"
				}
			]
		},
		{
			"number": 2900,
			"content": [
				{
					"text": "本辦法自發布日施行。"
				}
			]
		}
	]
}