{
	"pcode": "R0030106",
	"LawLevel": "命令",
	"name": "國軍上校以上軍官轉任公務人員考試規則",
	"category": [
		"考試",
		"考選部",
		"公務人員考試目"
	],
	"LawModifiedDate": "20221017",
	"attachments": {
		"0000327223": "附表一  國軍上校以上軍官轉任公務人員考試應試科目表.PDF",
		"0000071328": "附表二  學歷經歷審查評分表.PDF"
	},
	"histories": [
		"九十一年五月二十七日考試院考台組壹一字第 0910003148 號令訂定發布全文 13 條；並自發布日施行",
		"九十二年一月二十一日考試院考台組壹一字第 0920000309 號令修正發布第 2、7、9 條條文",
		"九十三年二月二十七日考試院考台組壹一字第 09300018141 號令修正發布第 4 條條文之附表一",
		"九十六年十一月七日考試院考臺組壹一字第 09600077011 號令修正發布第 4 條條文之附表一「國軍上校以上軍官轉任公務人員考試類科及應試科目表」",
		"九十八年十月三十日考試院考臺組壹一字第 09800086131 號令修正發布第 2、5 條條文及第 4 條條文之附表一",
		"一百零一年十月八日考試院考臺組壹一字第 10100086011 號令修正發布第 1 條條文及第 4 條之附表一「國軍上校以上軍官轉任公務人員考試類科及應試科目表」（新增廉政類科部分）",
		"一百零六年三月二十四日考試院考臺組壹一字第 10600015091 號令刪除發布原第 11、12 條條文；原第 13 條條文移列至第 11 條條文；並自發布日施行",
		"一百零七年四月二十三日考試院考臺組壹一字第 10700024411 號令修正發布第 2、3、10 條條文",
		"一百零七年七月二日考試院考臺組壹一字第 10700024481 號令修正發布第 8 條條文及第 4 條條文之附表一",
		"一百零八年十月二十八日考試院考臺組壹一字第 108000774 91 號令修正發布第 11 條條文及第 4 條條文之附表一；第 4 條條文之附表一自一百零九年一月十六日施行",
		"一百十一年十月十七日考試院考臺組壹一字第 11106000551 號令修正發布第 5、11 條條文及第 4 條條文之附表一；並自發布日施行"
	],
	"articles": [
		{
			"number": 100,
			"content": [
				{
					"text": "本規則依後備軍人轉任公職考試比敘條例第五條之一第一項規定訂定之。"
				}
			]
		},
		{
			"number": 200,
			"content": [
				{
					"text": "國軍上校以上軍官轉任公務人員考試（以下簡稱本考試），按應考人軍職官等官階分中將轉任考試、少將轉任考試、上校轉任考試。"
				},
				{
					"text": "前項各轉任考試應考資格如下：",
					"children": [
						{
							"text": "一、現任國軍中將軍官，已服滿法定役期，考試舉行前最近三年年終考績均列甲上以上，並具報考類科相關工作經驗三年以上者，得應中將轉任考試。"
						},
						{
							"text": "二、現任國軍少將軍官，已服滿法定役期，考試舉行前最近三年年終考績均列甲上以上，並具報考類科相關工作經驗三年以上者，得應少將轉任考試。"
						},
						{
							"text": "三、現任國軍上校軍官，已服滿法定役期，考試舉行前最近三年年終考績均列甲等以上，並具報考類科相關工作經驗三年以上者，得應上校轉任考試。"
						}
					]
				},
				{
					"text": "前項相關工作經驗之證明，由服務之總統府、國家安全會議、國家安全局、國防部、教育部、海洋委員會出具。"
				}
			]
		},
		{
			"number": 300,
			"content": [
				{
					"text": "本考試依轉任機關分別報名、分別錄取任用方式辦理。但轉任國軍退除役官兵輔導委員會、中央及直轄市政府役政、軍訓單位時，得不受限制。"
				}
			]
		},
		{
			"number": 400,
			"content": [
				{
					"text": "本考試之類科及應試科目，依附表一之規定。"
				},
				{
					"text": "前項考試類科須配合任用需要予以設置。"
				}
			]
		},
		{
			"number": 500,
			"content": [
				{
					"text": "本考試之方式，中將轉任考試併採筆試二科、審查知能有關學歷經歷證明及口試；少將轉任考試及上校轉任考試併採筆試二科及口試。"
				},
				{
					"text": "併採筆試二科、審查知能有關學歷經歷證明及口試者，筆試成績占百分之四十，審查知能有關學歷經歷證明成績占百分之四十，口試成績占百分之二十，合計為總成績；併採筆試二科及口試者，筆試成績占百分之六十，口試成績占百分之四十，合計為總成績；筆試成績，以各應試科目成績平均計算之。"
				}
			]
		},
		{
			"number": 600,
			"content": [
				{
					"text": "前條學歷經歷審查之評分項目及配分如下：",
					"children": [
						{
							"text": "一、學歷占三十分",
							"children": [
								{
									"text": "（一）修習學門與應考類科之相關性（依其科系所名稱、修習課程加以認定）：十二分。"
								},
								{
									"text": "（二）學歷等級：十八分",
									"children": [
										{
											"text": "1.博士學位：十五至十八分。"
										},
										{
											"text": "2.碩士學位：十二至十四分。"
										},
										{
											"text": "3.學士學位：十至十一分。"
										},
										{
											"text": "4.專科學校畢業：八至九分。"
										}
									]
								}
							]
						},
						{
							"text": "二、經歷占七十分",
							"children": [
								{
									"text": "（一）專業成就表現（應與應考等級、類科所需知能相關）：五十分。",
									"children": [
										{
											"text": "1.職務層級及工作表現：二十分。"
										},
										{
											"text": "2.獲頒勳章：十分。（以獲頒國光、青天白日、寶鼎、忠勇、雲麾、大同勳章為限，每乙座採計三至五分，最高以十分計）"
										},
										{
											"text": "3.主持或參與專業性研究計畫、在國內外專業性會議或刊物發表論文：十分。"
										},
										{
											"text": "4.公務人員考試及格證書或專門職業及技術人員考試及格證書或職業證照：十分。"
										}
									]
								},
								{
									"text": "（二）工作年資：（應與應考等級、類科所需知能相關）：二十分。（上校以上工作年資每滿一年計算一．五分，年資尾數滿半年以上未滿一年者，以一年計；未滿半年者，不予採計，最高以二十分計）學歷經歷審查評分表如附表二。"
								}
							]
						}
					]
				}
			]
		},
		{
			"number": 700,
			"content": [
				{
					"text": "應考人於報名時應繳驗下列費件：",
					"children": [
						{
							"text": "一、報名履歷表。"
						},
						{
							"text": "二、應考資格證明文件：上校以上軍階任官令、服滿法定役期證明、考試舉行前最近三年年終考績證明、服務機關出具之相關工作經驗證明。"
						},
						{
							"text": "三、最近一年內一吋正面脫帽半身照片。"
						},
						{
							"text": "四、報名費。"
						}
					]
				}
			]
		},
		{
			"number": 800,
			"content": [
				{
					"text": "本考試按轉任機關提報之職缺等級，擇優錄取。但應考人考試總成績未滿五十分或筆試成績有一科為零分或口試成績未滿六十分者，均不予錄取。缺考之科目，視為零分。"
				}
			]
		},
		{
			"number": 900,
			"content": [
				{
					"text": "本考試錄取人員於接受分發報到後，由轉任機關報請考試院發給考試及格證書。"
				},
				{
					"text": "前項錄取人員於轉任機關分發通知到達後一個月內未報到者，不再分發任用，亦不發給考試及格證書。"
				}
			]
		},
		{
			"number": 1000,
			"content": [
				{
					"text": "本考試及格人員，按報名轉任機關，由國家安全會議、國家安全局、國防部、國軍退除役官兵輔導委員會、海洋委員會及其所屬機關（構）、中央及直轄市政府役政、軍訓單位任用，並僅得於各轉任機關間轉調。但轉調海洋委員會及其所屬機關（構），以具有航海（空）、造船、輪機、資訊、電子等特殊專長者為限。"
				},
				{
					"text": "前項轉調之限制，應於考試及格證書註明，並函請銓敘部查照。"
				}
			]
		},
		{
			"number": 1100,
			"content": [
				{
					"text": "本規則自發布日施行。"
				}
			]
		}
	]
}