{
	"法規性質": "命令",
	"法規名稱": "專門職業及技術人員考試審議委員會組織規程",
	"法規網址": "https://law.moj.gov.tw/LawClass/LawOldVer.aspx?PCODE=R0000009&LNNDATE=20030923&LSER=001",
	"法規類別": "考試＞考選部＞組織目",
	"異動日期": "20030923",
	"法規內容": [
		{
			"條號": "第 1 條",
			"條文內容": "本規程依考選部組織法第十九條規定訂定之。"
		},
		{
			"條號": "第 2 條",
			"條文內容": "考選部為辦理專門職業及技術人員考試減免應試科目案件之審議與專門職\r\n業及技術人員考試法修正公布施行前申請檢覈經核定准予筆試或面試者筆\r\n試成績之審議，得設下列各專門職業及技術人員考試審議委員會 (以下簡\r\n稱審議委員會) ：                                                \r\n一  律師考試審議委員會。                                        \r\n二  會計師考試審議委員會。                                      \r\n三  建築師考試審議委員會。                                      \r\n四  技師考試審議委員會。                                        \r\n五  醫事人員考試審議委員會。                                    \r\n六  中醫師考試審議委員會。                                      \r\n七  營養師考試審議委員會。                                      \r\n八  獸醫人員考試審議委員會。                                    \r\n九  漁船船員考試審議委員會。                                    \r\n十  社會工作師考試審議委員會。                                \r\n十一  地政士考試審議委員會。                                    \r\n十二  心理師考試審議委員會。"
		},
		{
			"條號": "第 3 條",
			"條文內容": "各審議委員會置主任委員一人，由考選部次長兼任。副主任委員一至二人\r\n，委員若干人，由考選部就部內及有關職業主管機關簡任以上高級人員暨\r\n有關學者專家遴聘之。其資格準用典試法有關典試委員資格之規定，並報\r\n考試院備查。\r\n前項人員之任期為一年，得連任。有關職業主管機關簡任以上高級人員之\r\n任期，隨其本職異動而更易。\r\n審議委員會委員為無給職，但得酌支出席費。"
		},
		{
			"條號": "第 4 條",
			"條文內容": "申請減免應試科目案件，經主管司初審並簽擬意見，陳由主任委員分配各\r\n委員複審，加具意見後，提審議委員會審議。"
		},
		{
			"條號": "第 5 條",
			"條文內容": "審議委員會開會時，由主任委員為主席。主任委員不能出席時，由副主任\r\n委員為主席。主任委員及副主任委員均不能出席時，由委員公推一人為主\r\n席。\r\n委員應親自出席，不得委託代理。"
		},
		{
			"條號": "第 6 條",
			"條文內容": "審議委員會開會時，須由委員過半數之出席，方得開議。經出席委員過半\r\n數之同意，方得決議，可否同數時取決於主席。"
		},
		{
			"條號": "第 7 條",
			"條文內容": "審議委員會主任委員、副主任委員及委員，對於其本人、配偶或三親等內\r\n之血親、姻親，申請減免應試科目時，應行迴避。\r\n審議委員會主任委員、副主任委員及委員為申請人現任機關直屬長官，或\r\n為其學位論文之指導教授者亦同。"
		},
		{
			"條號": "第 8 條",
			"條文內容": "審議委員會審議結果依下列規定辦理：\r\n一  經核定准予全部科目免試者，由考選部報請考試院發給及格證書，並\r\n    函相關職業主管機關查照。\r\n二  經核定准予部分科目免試者，由考選部通知申請人，並依規定參加考\r\n    試。\r\n三  經核定不合格者，應予退件。\r\n四  本法修正公布施行前申請檢覈經核定准予筆試或面試者，其筆試成績\r\n    及格經審議後，由考選部報請考試院發給檢覈及格證書，並函相關職\r\n    業主管機關查照。\r\n前項審議結果，由考選部核定，並報請考試院備查。"
		},
		{
			"條號": "第 9 條",
			"條文內容": "本規程自中華民國九十年一月一日施行。"
		}
	]
}