{
	"pcode": "D0050202",
	"type": "命令",
	"title": "合作社決算報表查核辦法",
	"url": "https://law.moj.gov.tw/LawClass/LawAll.aspx?pcode=D0050202",
	"category": [
		"行政",
		"內政部",
		"合作及人民團體目"
	],
	"lastUpdate": "20160929",
	"isTranslated": false,
	"history": [
		"一百零五年九月二十九日內政部內授中團字第 1051403131 號令訂定發布全文 9 條；並自發布日施行"
	],
	"theAct": {
		"title": "合作社法"
	},
	"divisions": [],
	"articles": [
		{
			"number": 100,
			"content": "本辦法依合作社法（以下簡稱本法）第三十六條第四項規定訂定之。"
		},
		{
			"number": 200,
			"content": "本辦法所稱決算報表，指本法第三十六條第一項之業務報告書、資產負債表、收支餘絀表、財產目錄及結餘分配或短絀分擔案等法定書類。"
		},
		{
			"number": 300,
			"content": "合作社決算報表查核種類，分為下列二種：\r\n一、定期查核：根據合作社報送之決算報表所為之查核。\r\n二、專案查核：對重大事項或主管機關因實際需要所為之查核。"
		},
		{
			"number": 400,
			"content": "主管機關除書面查核合作社決算報表外，得派員實地查核，必要時，並得會同有關機關辦理，合作社不得規避、妨礙或拒絕查核，並應提供必要之協助。"
		},
		{
			"number": 500,
			"content": "主管機關辦理第三條第一款派員實地查核合作社決算報表時，應於七日前通知，並依指定日期前往辦理。"
		},
		{
			"number": 600,
			"content": "主管機關查核合作社決算報表完畢後，除有本法第七十四條第一款所定為不實記載情事外，應將查核結果及改善事項，以書面通知合作社。\r\n前項改善事項，合作社應以書面答復；其改善結果並得作為年度考核之參考。"
		},
		{
			"number": 700,
			"content": "主管機關得派員監督合作社決算報表之製作及記載。"
		},
		{
			"number": 800,
			"content": "本辦法於合作社聯合社，準用之。"
		},
		{
			"number": 900,
			"content": "本辦法自發布日施行。"
		}
	]
}